ebird/api/data/__init__.py
ebird/api/data/admin.py
ebird/api/data/apps.py
ebird/api/data/factories.py
ebird/api/data/faker_providers.py
ebird/api/data/fields.py
ebird/api/data/loaders.py
ebird/api/data/widgets.py
ebird/api/data/fixtures/README.md
ebird/api/data/fixtures/generate_portugal_data.py
ebird/api/data/fixtures/portugal_observations.json
ebird/api/data/locale/en/LC_MESSAGES/django.mo
ebird/api/data/locale/en/LC_MESSAGES/django.po
ebird/api/data/management/__init__.py
ebird/api/data/management/commands/__init__.py
ebird/api/data/management/commands/add_checklists.py
ebird/api/data/migrations/0001_initial.py
ebird/api/data/migrations/0002_expand_filter.py
ebird/api/data/migrations/0003_remove_checklist_published_and_more.py
ebird/api/data/migrations/0004_remove_observer_multiple.py
ebird/api/data/migrations/__init__.py
ebird/api/data/models/__init__.py
ebird/api/data/models/checklist.py
ebird/api/data/models/country.py
ebird/api/data/models/county.py
ebird/api/data/models/location.py
ebird/api/data/models/models.md
ebird/api/data/models/observation.py
ebird/api/data/models/observer.py
ebird/api/data/models/species.py
ebird/api/data/models/state.py
ebird/api/data/templates/admin/data/species/change_list_object_tools.html
ebird/api/data/templates/admin/data/species/fetch_species.html
ebird/api/data/templates/data/widgets/translation_field.html
ebird_api_data-0.5.0.dist-info/METADATA
ebird_api_data-0.5.0.dist-info/WHEEL
ebird_api_data-0.5.0.dist-info/licenses/LICENSE
ebird_api_data-0.5.0.dist-info/RECORD
