Metadata-Version: 2.4
Name: ebird-api-data
Version: 0.5.0
Summary: eBird API Data is a reusable Django app for loading data from eBird into a database.
Author-email: Stuart MacKay <smackay@flagstonesoftware.com>
License-Expression: MIT
License-File: LICENSE
Keywords: Django,checklists,eBird,models,observations,species
Classifier: Development Status :: 5 - Production/Stable
Classifier: Framework :: Django
Classifier: Framework :: Django :: 4.2
Classifier: Framework :: Django :: 5.0
Classifier: Framework :: Django :: 5.1
Classifier: Framework :: Django :: 5.2
Classifier: Intended Audience :: Science/Research
Classifier: Natural Language :: English
Classifier: Programming Language :: Python :: 3.10
Classifier: Programming Language :: Python :: 3.11
Classifier: Programming Language :: Python :: 3.12
Classifier: Programming Language :: Python :: 3.13
Classifier: Topic :: Scientific/Engineering
Classifier: Topic :: Scientific/Engineering :: Information Analysis
Requires-Python: >=3.10
Requires-Dist: beautifulsoup4>=4.13.3
Requires-Dist: django>=4.2
Requires-Dist: ebird-api-requests==4.0.2
Requires-Dist: lxml>=6.0.0
